[{"SID":"1938266N17148","SEASON":"1938","NUMBER":"50","BASIN":"WP","SUBBASIN":"MM","NAME":"NOT_NAMED","ISO_TIME":"1938-09-23 09:00:00","NATURE":"NR","LAT":"17.2000","LON":"148.000","TRACK_TYPE":"main","DIST2LAND":"2133","LANDFALL":"2106","IFLAG":"__________O___","USA_SSHS":"-5","TD9636_LAT":"17.2000","TD9636_LON":"148.000","TD9636_STAGE":"7","STORM_SPEED":"29","STORM_DIR":"260"},{"SID":"1938266N17148","SEASON":"1938","NUMBER":"50","BASIN":"WP","SUBBASIN":"MM","NAME":"NOT_NAMED","ISO_TIME":"1938-09-23 12:00:00","NATURE":"NR","LAT":"16.9540","LON":"146.493","TRACK_TYPE":"main","DIST2LAND":"2103","LANDFALL":"2074","IFLAG":"__________P___","USA_SSHS":"-5","TD9636_LAT":"16.9540","TD9636_LON":"146.493","TD9636_STAGE":"7","STORM_SPEED":"29","STORM_DIR":"261"},{"SID":"1938266N17148","SEASON":"1938","NUMBER":"50","BASIN":"WP","SUBBASIN":"MM","NAME":"NOT_NAMED","ISO_TIME":"1938-09-23 15:00:00","NATURE":"NR","LAT":"16.7408","LON":"145.061","TRACK_TYPE":"main","DIST2LAND":"2084","LANDFALL":"2031","IFLAG":"__________P___","USA_SSHS":"-5","TD9636_LAT":"16.7408","TD9636_LON":"145.061","TD9636_STAGE":"7","STORM_SPEED":"26","STORM_DIR":"262"},{"SID":"1938266N17148","SEASON":"1938","NUMBER":"50","BASIN":"WP","SUBBASIN":"MM","NAME":"NOT_NAMED","ISO_TIME":"1938-09-23 18:00:00","NATURE":"NR","LAT":"16.6070","LON":"143.774","TRACK_TYPE":"main","DIST2LAND":"2031","LANDFALL":"1927","IFLAG":"__________P___","USA_SSHS":"-5","TD9636_LAT":"16.6070","TD9636_LON":"143.774","TD9636_STAGE":"7","STORM_SPEED":"23","STORM_DIR":"266"},{"SID":"1938266N17148","SEASON":"1938","NUMBER":"50","BASIN":"WP","SUBBASIN":"MM","NAME":"NOT_NAMED","ISO_TIME":"1938-09-23 21:00:00","NATURE":"NR","LAT":"16.6000","LON":"142.700","TRACK_TYPE":"main","DIST2LAND":"1916","LANDFALL":"1836","IFLAG":"__________O___","USA_SSHS":"-5","TD9636_LAT":"16.6000","TD9636_LON":"142.700","TD9636_STAGE":"7","STORM_SPEED":"18","STORM_DIR":"274"},{"SID":"1938266N17148","SEASON":"1938","NUMBER":"50","BASIN":"WP","SUBBASIN":"MM","NAME":"NOT_NAMED","ISO_TIME":"1938-09-24 00:00:00","NATURE":"NR","LAT":"16.7479","LON":"141.878","TRACK_TYPE":"main","DIST2LAND":"1836","LANDFALL":"1782","IFLAG":"__________P___","USA_SSHS":"-5","TD9636_LAT":"16.7479","TD9636_LON":"141.878","TD9636_STAGE":"7","STORM_SPEED":"15","STORM_DIR":"286"},{"SID":"1938266N17148","SEASON":"1938","NUMBER":"50","BASIN":"WP","SUBBASIN":"MM","NAME":"NOT_NAMED","ISO_TIME":"1938-09-24 03:00:00","NATURE":"NR","LAT":"16.9975","LON":"141.226","TRACK_TYPE":"main","DIST2LAND":"1772","LANDFALL":"1727","IFLAG":"__________P___","USA_SSHS":"-5","TD9636_LAT":"16.9975","TD9636_LON":"141.226","TD9636_STAGE":"7","STORM_SPEED":"13","STORM_DIR":"294"},{"SID":"1938266N17148","SEASON":"1938","NUMBER":"50","BASIN":"WP","SUBBASIN":"MM","NAME":"NOT_NAMED","ISO_TIME":"1938-09-24 06:00:00","NATURE":"NR","LAT":"17.2737","LON":"140.637","TRACK_TYPE":"main","DIST2LAND":"1720","LANDFALL":"1667","IFLAG":"__________P___","USA_SSHS":"-5","TD9636_LAT":"17.2737","TD9636_LON":"140.637","TD9636_STAGE":"7","STORM_SPEED":"13","STORM_DIR":"293"},{"SID":"1938266N17148","SEASON":"1938","NUMBER":"50","BASIN":"WP","SUBBASIN":"MM","NAME":"NOT_NAMED","ISO_TIME":"1938-09-24 09:00:00","NATURE":"NR","LAT":"17.5000","LON":"140.000","TRACK_TYPE":"main","DIST2LAND":"1667","LANDFALL":"1591","IFLAG":"__________O___","USA_SSHS":"-5","TD9636_LAT":"17.5000","TD9636_LON":"140.000","TD9636_STAGE":"7","STORM_SPEED":"15","STORM_DIR":"281"},{"SID":"1938266N17148","SEASON":"1938","NUMBER":"50","BASIN":"WP","SUBBASIN":"MM","NAME":"NOT_NAMED","ISO_TIME":"1938-09-24 12:00:00","NATURE":"NR","LAT":"17.5544","LON":"139.098","TRACK_TYPE":"main","DIST2LAND":"1581","LANDFALL":"1488","IFLAG":"__________P___","USA_SSHS":"-5","TD9636_LAT":"17.5544","TD9636_LON":"139.098","TD9636_STAGE":"7","STORM_SPEED":"18","STORM_DIR":"272"},{"SID":"1938266N17148","SEASON":"1938","NUMBER":"50","BASIN":"WP","SUBBASIN":"MM","NAME":"NOT_NAMED","ISO_TIME":"1938-09-24 15:00:00","NATURE":"NR","LAT":"17.5478","LON":"138.146","TRACK_TYPE":"main","DIST2LAND":"1478","LANDFALL":"1400","IFLAG":"__________P___","USA_SSHS":"-5","TD9636_LAT":"17.5478","TD9636_LON":"138.146","TD9636_STAGE":"7","STORM_SPEED":"18","STORM_DIR":"269"},{"SID":"1938266N17148","SEASON":"1938","NUMBER":"50","BASIN":"WP","SUBBASIN":"MM","NAME":"NOT_NAMED","ISO_TIME":"1938-09-24 18:00:00","NATURE":"NR","LAT":"17.5170","LON":"137.220","TRACK_TYPE":"main","DIST2LAND":"1390","LANDFALL":"1313","IFLAG":"__________P___","USA_SSHS":"-5","TD9636_LAT":"17.5170","TD9636_LON":"137.220","TD9636_STAGE":"7","STORM_SPEED":"17","STORM_DIR":"268"},{"SID":"1938266N17148","SEASON":"1938","NUMBER":"50","BASIN":"WP","SUBBASIN":"MM","NAME":"NOT_NAMED","ISO_TIME":"1938-09-24 21:00:00","NATURE":"NR","LAT":"17.5000","LON":"136.400","TRACK_TYPE":"main","DIST2LAND":"1313","LANDFALL":"1255","IFLAG":"__________O___","USA_SSHS":"-5","TD9636_LAT":"17.5000","TD9636_LON":"136.400","TD9636_STAGE":"7","STORM_SPEED":"14","STORM_DIR":"268"},{"SID":"1938266N17148","SEASON":"1938","NUMBER":"50","BASIN":"WP","SUBBASIN":"MM","NAME":"NOT_NAMED","ISO_TIME":"1938-09-25 00:00:00","NATURE":"NR","LAT":"17.4696","LON":"135.800","TRACK_TYPE":"main","DIST2LAND":"1255","LANDFALL":"1208","IFLAG":"__________P___","USA_SSHS":"-5","TD9636_LAT":"17.4696","TD9636_LON":"135.800","TD9636_STAGE":"7","STORM_SPEED":"10","STORM_DIR":"269"},{"SID":"1938266N17148","SEASON":"1938","NUMBER":"50","BASIN":"WP","SUBBASIN":"MM","NAME":"NOT_NAMED","ISO_TIME":"1938-09-25 03:00:00","NATURE":"NR","LAT":"17.4743","LON":"135.307","TRACK_TYPE":"main","DIST2LAND":"1208","LANDFALL":"1171","IFLAG":"__________P___","USA_SSHS":"-5","TD9636_LAT":"17.4743","TD9636_LON":"135.307","TD9636_STAGE":"7","STORM_SPEED":"9","STORM_DIR":"276"},{"SID":"1938266N17148","SEASON":"1938","NUMBER":"50","BASIN":"WP","SUBBASIN":"MM","NAME":"NOT_NAMED","ISO_TIME":"1938-09-25 06:00:00","NATURE":"NR","LAT":"17.5670","LON":"134.861","TRACK_TYPE":"main","DIST2LAND":"1177","LANDFALL":"1143","IFLAG":"__________P___","USA_SSHS":"-5","TD9636_LAT":"17.5670","TD9636_LON":"134.861","TD9636_STAGE":"7","STORM_SPEED":"9","STORM_DIR":"291"},{"SID":"1938266N17148","SEASON":"1938","NUMBER":"50","BASIN":"WP","SUBBASIN":"MM","NAME":"NOT_NAMED","ISO_TIME":"1938-09-25 09:00:00","NATURE":"NR","LAT":"17.8000","LON":"134.400","TRACK_TYPE":"main","DIST2LAND":"1143","LANDFALL":"1113","IFLAG":"__________O___","USA_SSHS":"-5","TD9636_LAT":"17.8000","TD9636_LON":"134.400","TD9636_STAGE":"7","STORM_SPEED":"12","STORM_DIR":"305"},{"SID":"1938266N17148","SEASON":"1938","NUMBER":"50","BASIN":"WP","SUBBASIN":"MM","NAME":"NOT_NAMED","ISO_TIME":"1938-09-25 12:00:00","NATURE":"NR","LAT":"18.2765","LON":"133.795","TRACK_TYPE":"main","DIST2LAND":"1118","LANDFALL":"1087","IFLAG":"__________P___","USA_SSHS":"-5","TD9636_LAT":"18.2765","TD9636_LON":"133.795","TD9636_STAGE":"7","STORM_SPEED":"16","STORM_DIR":"313"},{"SID":"1938266N17148","SEASON":"1938","NUMBER":"50","BASIN":"WP","SUBBASIN":"MM","NAME":"NOT_NAMED","ISO_TIME":"1938-09-25 15:00:00","NATURE":"NR","LAT":"18.8835","LON":"133.167","TRACK_TYPE":"main","DIST2LAND":"1092","LANDFALL":"1071","IFLAG":"__________P___","USA_SSHS":"-5","TD9636_LAT":"18.8835","TD9636_LON":"133.167","TD9636_STAGE":"7","STORM_SPEED":"17","STORM_DIR":"317"},{"SID":"1938266N17148","SEASON":"1938","NUMBER":"50","BASIN":"WP","SUBBASIN":"MM","NAME":"NOT_NAMED","ISO_TIME":"1938-09-25 18:00:00","NATURE":"NR","LAT":"19.5236","LON":"132.555","TRACK_TYPE":"main","DIST2LAND":"1074","LANDFALL":"1035","IFLAG":"__________P___","USA_SSHS":"-5","TD9636_LAT":"19.5236","TD9636_LON":"132.555","TD9636_STAGE":"7","STORM_SPEED":"16","STORM_DIR":"318"},{"SID":"1938266N17148","SEASON":"1938","NUMBER":"50","BASIN":"WP","SUBBASIN":"MM","NAME":"NOT_NAMED","ISO_TIME":"1938-09-25 21:00:00","NATURE":"NR","LAT":"20.1000","LON":"132.000","TRACK_TYPE":"main","DIST2LAND":"1035","LANDFALL":"1010","IFLAG":"__________O___","USA_SSHS":"-5","TD9636_LAT":"20.1000","TD9636_LON":"132.000","TD9636_STAGE":"7","STORM_SPEED":"13","STORM_DIR":"319"},{"SID":"1938266N17148","SEASON":"1938","NUMBER":"50","BASIN":"WP","SUBBASIN":"MM","NAME":"NOT_NAMED","ISO_TIME":"1938-09-26 00:00:00","NATURE":"NR","LAT":"20.4999","LON":"131.663","TRACK_TYPE":"main","DIST2LAND":"1012","LANDFALL":"990","IFLAG":"__________P___","USA_SSHS":"-5","TD9636_LAT":"20.4999","TD9636_LON":"131.663","TD9636_STAGE":"7","STORM_SPEED":"9","STORM_DIR":"321"},{"SID":"1938266N17148","SEASON":"1938","NUMBER":"50","BASIN":"WP","SUBBASIN":"MM","NAME":"NOT_NAMED","ISO_TIME":"1938-09-26 03:00:00","NATURE":"NR","LAT":"20.8220","LON":"131.374","TRACK_TYPE":"main","DIST2LAND":"990","LANDFALL":"959","IFLAG":"__________P___","USA_SSHS":"-5","TD9636_LAT":"20.8220","TD9636_LON":"131.374","TD9636_STAGE":"7","STORM_SPEED":"8","STORM_DIR":"314"},{"SID":"1938266N17148","SEASON":"1938","NUMBER":"50","BASIN":"WP","SUBBASIN":"MM","NAME":"NOT_NAMED","ISO_TIME":"1938-09-26 06:00:00","NATURE":"NR","LAT":"21.0833","LON":"131.023","TRACK_TYPE":"main","DIST2LAND":"959","LANDFALL":"916","IFLAG":"__________P___","USA_SSHS":"-5","TD9636_LAT":"21.0833","TD9636_LON":"131.023","TD9636_STAGE":"7","STORM_SPEED":"9","STORM_DIR":"300"},{"SID":"1938266N17148","SEASON":"1938","NUMBER":"50","BASIN":"WP","SUBBASIN":"MM","NAME":"NOT_NAMED","ISO_TIME":"1938-09-26 09:00:00","NATURE":"NR","LAT":"21.3000","LON":"130.500","TRACK_TYPE":"main","DIST2LAND":"916","LANDFALL":"847","IFLAG":"__________O___","USA_SSHS":"-5","TD9636_LAT":"21.3000","TD9636_LON":"130.500","TD9636_STAGE":"7","STORM_SPEED":"14","STORM_DIR":"290"},{"SID":"1938266N17148","SEASON":"1938","NUMBER":"50","BASIN":"WP","SUBBASIN":"MM","NAME":"NOT_NAMED","ISO_TIME":"1938-09-26 12:00:00","NATURE":"NR","LAT":"21.5590","LON":"129.595","TRACK_TYPE":"main","DIST2LAND":"842","LANDFALL":"748","IFLAG":"__________P___","USA_SSHS":"-5","TD9636_LAT":"21.5590","TD9636_LON":"129.595","TD9636_STAGE":"7","STORM_SPEED":"19","STORM_DIR":"284"},{"SID":"1938266N17148","SEASON":"1938","NUMBER":"50","BASIN":"WP","SUBBASIN":"MM","NAME":"NOT_NAMED","ISO_TIME":"1938-09-26 15:00:00","NATURE":"NR","LAT":"21.7646","LON":"128.521","TRACK_TYPE":"main","DIST2LAND":"738","LANDFALL":"640","IFLAG":"__________P___","USA_SSHS":"-5","TD9636_LAT":"21.7646","TD9636_LON":"128.521","TD9636_STAGE":"7","STORM_SPEED":"21","STORM_DIR":"279"},{"SID":"1938266N17148","SEASON":"1938","NUMBER":"50","BASIN":"WP","SUBBASIN":"MM","NAME":"NOT_NAMED","ISO_TIME":"1938-09-26 18:00:00","NATURE":"NR","LAT":"21.8872","LON":"127.411","TRACK_TYPE":"main","DIST2LAND":"630","LANDFALL":"530","IFLAG":"__________P___","USA_SSHS":"-5","TD9636_LAT":"21.8872","TD9636_LON":"127.411","TD9636_STAGE":"7","STORM_SPEED":"20","STORM_DIR":"274"},{"SID":"1938266N17148","SEASON":"1938","NUMBER":"50","BASIN":"WP","SUBBASIN":"MM","NAME":"NOT_NAMED","ISO_TIME":"1938-09-26 21:00:00","NATURE":"NR","LAT":"21.9000","LON":"126.400","TRACK_TYPE":"main","DIST2LAND":"530","LANDFALL":"478","IFLAG":"__________O___","USA_SSHS":"-5","TD9636_LAT":"21.9000","TD9636_LON":"126.400","TD9636_STAGE":"7","STORM_SPEED":"16","STORM_DIR":"262"},{"SID":"1938266N17148","SEASON":"1938","NUMBER":"50","BASIN":"WP","SUBBASIN":"MM","NAME":"NOT_NAMED","ISO_TIME":"1938-09-27 00:00:00","NATURE":"NR","LAT":"21.6633","LON":"125.749","TRACK_TYPE":"main","DIST2LAND":"468","LANDFALL":"434","IFLAG":"__________P___","USA_SSHS":"-5","TD9636_LAT":"21.6633","TD9636_LON":"125.749","TD9636_STAGE":"7","STORM_SPEED":"12","STORM_DIR":"243"},{"SID":"1938266N17148","SEASON":"1938","NUMBER":"50","BASIN":"WP","SUBBASIN":"MM","NAME":"NOT_NAMED","ISO_TIME":"1938-09-27 03:00:00","NATURE":"NR","LAT":"21.3445","LON":"125.206","TRACK_TYPE":"main","DIST2LAND":"439","LANDFALL":"392","IFLAG":"__________P___","USA_SSHS":"-5","TD9636_LAT":"21.3445","TD9636_LON":"125.206","TD9636_STAGE":"7","STORM_SPEED":"12","STORM_DIR":"240"},{"SID":"1938266N17148","SEASON":"1938","NUMBER":"50","BASIN":"WP","SUBBASIN":"MM","NAME":"NOT_NAMED","ISO_TIME":"1938-09-27 06:00:00","NATURE":"NR","LAT":"21.0789","LON":"124.660","TRACK_TYPE":"main","DIST2LAND":"392","LANDFALL":"336","IFLAG":"__________P___","USA_SSHS":"-5","TD9636_LAT":"21.0789","TD9636_LON":"124.660","TD9636_STAGE":"7","STORM_SPEED":"12","STORM_DIR":"253"},{"SID":"1938266N17148","SEASON":"1938","NUMBER":"50","BASIN":"WP","SUBBASIN":"MM","NAME":"NOT_NAMED","ISO_TIME":"1938-09-27 09:00:00","NATURE":"NR","LAT":"21.0000","LON":"124.000","TRACK_TYPE":"main","DIST2LAND":"336","LANDFALL":"227","IFLAG":"__________O___","USA_SSHS":"-5","TD9636_LAT":"21.0000","TD9636_LON":"124.000","TD9636_STAGE":"7","STORM_SPEED":"16","STORM_DIR":"280"},{"SID":"1938266N17148","SEASON":"1938","NUMBER":"50","BASIN":"WP","SUBBASIN":"MM","NAME":"NOT_NAMED","ISO_TIME":"1938-09-27 12:00:00","NATURE":"NR","LAT":"21.3484","LON":"122.958","TRACK_TYPE":"main","DIST2LAND":"227","LANDFALL":"103","IFLAG":"__________P___","USA_SSHS":"-5","TD9636_LAT":"21.3484","TD9636_LON":"122.958","TD9636_STAGE":"7","STORM_SPEED":"22","STORM_DIR":"293"},{"SID":"1938266N17148","SEASON":"1938","NUMBER":"50","BASIN":"WP","SUBBASIN":"MM","NAME":"NOT_NAMED","ISO_TIME":"1938-09-27 15:00:00","NATURE":"NR","LAT":"21.8759","LON":"121.797","TRACK_TYPE":"main","DIST2LAND":"92","LANDFALL":"0","IFLAG":"__________P___","USA_SSHS":"-5","TD9636_LAT":"21.8759","TD9636_LON":"121.797","TD9636_STAGE":"7","STORM_SPEED":"24","STORM_DIR":"297"},{"SID":"1938266N17148","SEASON":"1938","NUMBER":"50","BASIN":"WP","SUBBASIN":"MM","NAME":"NOT_NAMED","ISO_TIME":"1938-09-27 18:00:00","NATURE":"NR","LAT":"22.4394","LON":"120.660","TRACK_TYPE":"main","DIST2LAND":"0","LANDFALL":"0","IFLAG":"__________P___","USA_SSHS":"-5","TD9636_LAT":"22.4394","TD9636_LON":"120.660","TD9636_STAGE":"7","STORM_SPEED":"22","STORM_DIR":"298"},{"SID":"1938266N17148","SEASON":"1938","NUMBER":"50","BASIN":"WP","SUBBASIN":"MM","NAME":"NOT_NAMED","ISO_TIME":"1938-09-27 21:00:00","NATURE":"NR","LAT":"22.9000","LON":"119.700","TRACK_TYPE":"main","DIST2LAND":"46","LANDFALL":"46","IFLAG":"__________O___","USA_SSHS":"-5","TD9636_LAT":"22.9000","TD9636_LON":"119.700","TD9636_STAGE":"7","STORM_SPEED":"15","STORM_DIR":"297"},{"SID":"1938266N17148","SEASON":"1938","NUMBER":"50","BASIN":"WP","SUBBASIN":"MM","NAME":"NOT_NAMED","ISO_TIME":"1938-09-28 00:00:00","NATURE":"NR","LAT":"23.1178","LON":"119.227","TRACK_TYPE":"main","DIST2LAND":"92","LANDFALL":"92","IFLAG":"__________P___","USA_SSHS":"-5","TD9636_LAT":"23.1178","TD9636_LON":"119.227","TD9636_STAGE":"7","STORM_SPEED":"8","STORM_DIR":"294"},{"SID":"1938266N17148","SEASON":"1938","NUMBER":"50","BASIN":"WP","SUBBASIN":"MM","NAME":"NOT_NAMED","ISO_TIME":"1938-09-28 03:00:00","NATURE":"NR","LAT":"23.2152","LON":"118.933","TRACK_TYPE":"main","DIST2LAND":"122","LANDFALL":"120","IFLAG":"__________P___","USA_SSHS":"-5","TD9636_LAT":"23.2152","TD9636_LON":"118.933","TD9636_STAGE":"7","STORM_SPEED":"5","STORM_DIR":"279"},{"SID":"1938266N17148","SEASON":"1938","NUMBER":"50","BASIN":"WP","SUBBASIN":"MM","NAME":"NOT_NAMED","ISO_TIME":"1938-09-28 06:00:00","NATURE":"NR","LAT":"23.2054","LON":"118.648","TRACK_TYPE":"main","DIST2LAND":"112","LANDFALL":"90","IFLAG":"__________P___","USA_SSHS":"-5","TD9636_LAT":"23.2054","TD9636_LON":"118.648","TD9636_STAGE":"7","STORM_SPEED":"7","STORM_DIR":"260"},{"SID":"1938266N17148","SEASON":"1938","NUMBER":"50","BASIN":"WP","SUBBASIN":"MM","NAME":"NOT_NAMED","ISO_TIME":"1938-09-28 09:00:00","NATURE":"NR","LAT":"23.1000","LON":"118.200","TRACK_TYPE":"main","DIST2LAND":"90","LANDFALL":"78","IFLAG":"__________O___","USA_SSHS":"-5","TD9636_LAT":"23.1000","TD9636_LON":"118.200","TD9636_STAGE":"7","STORM_SPEED":"11","STORM_DIR":"255"},{"SID":"1938266N17148","SEASON":"1938","NUMBER":"50","BASIN":"WP","SUBBASIN":"MM","NAME":"NOT_NAMED","ISO_TIME":"1938-09-28 12:00:00","NATURE":"NR","LAT":"22.9099","LON":"117.461","TRACK_TYPE":"main","DIST2LAND":"78","LANDFALL":"22","IFLAG":"__________P___","USA_SSHS":"-5","TD9636_LAT":"22.9099","TD9636_LON":"117.461","TD9636_STAGE":"7","STORM_SPEED":"17","STORM_DIR":"254"},{"SID":"1938266N17148","SEASON":"1938","NUMBER":"50","BASIN":"WP","SUBBASIN":"MM","NAME":"NOT_NAMED","ISO_TIME":"1938-09-28 15:00:00","NATURE":"NR","LAT":"22.6508","LON":"116.474","TRACK_TYPE":"main","DIST2LAND":"22","LANDFALL":"22","IFLAG":"__________P___","USA_SSHS":"-5","TD9636_LAT":"22.6508","TD9636_LON":"116.474","TD9636_STAGE":"7","STORM_SPEED":"21","STORM_DIR":"254"},{"SID":"1938266N17148","SEASON":"1938","NUMBER":"50","BASIN":"WP","SUBBASIN":"MM","NAME":"NOT_NAMED","ISO_TIME":"1938-09-28 18:00:00","NATURE":"NR","LAT":"22.3409","LON":"115.325","TRACK_TYPE":"main","DIST2LAND":"44","LANDFALL":"22","IFLAG":"__________P___","USA_SSHS":"-5","TD9636_LAT":"22.3409","TD9636_LON":"115.325","TD9636_STAGE":"7","STORM_SPEED":"23","STORM_DIR":"253"},{"SID":"1938266N17148","SEASON":"1938","NUMBER":"50","BASIN":"WP","SUBBASIN":"MM","NAME":"NOT_NAMED","ISO_TIME":"1938-09-28 21:00:00","NATURE":"NR","LAT":"22.0000","LON":"114.100","TRACK_TYPE":"main","DIST2LAND":"39","IFLAG":"__________O___","USA_SSHS":"-5","TD9636_LAT":"22.0000","TD9636_LON":"114.100","TD9636_STAGE":"7","STORM_SPEED":"24","STORM_DIR":"253"}]